llm_math-0.2.0.dist-info/METADATA
llm_math-0.2.0.dist-info/WHEEL
llm_math-0.2.0.dist-info/entry_points.txt
llm_math/.DS_Store
llm_math/__init__.py
llm_math/data/.DS_Store
llm_math/data/4o_correct/.DS_Store
llm_math/data/4o_correct/test.jsonl
llm_math/data/4o_wrong/.DS_Store
llm_math/data/4o_wrong/test.jsonl
llm_math/data/asdiv/test.jsonl
llm_math/data/gsm8k/test.jsonl
llm_math/data/gsm8k/train.jsonl
llm_math/data/gsm_hard/test.jsonl
llm_math/data/hungarian_exam/README.md
llm_math/data/hungarian_exam/test.jsonl
llm_math/data/math/test.jsonl
llm_math/data/math/train.jsonl
llm_math/data/math_oai/test.jsonl
llm_math/data/math_oai_correct/.DS_Store
llm_math/data/math_oai_correct/test.jsonl
llm_math/data/math_oai_wrong/test.jsonl
llm_math/data/math_oai_wrong_50/test.jsonl
llm_math/data/mathqa/test.jsonl
llm_math/data/mawps/addsub.jsonl
llm_math/data/mawps/multiarith.jsonl
llm_math/data/mawps/singleeq.jsonl
llm_math/data/mawps/singleop.jsonl
llm_math/data/mawps/test.jsonl
llm_math/data/mmlu_stem/test.jsonl
llm_math/data/ocw/README.md
llm_math/data/ocw/test.jsonl
llm_math/data/sat_math/test.jsonl
llm_math/data/svamp/test.jsonl
llm_math/data/tabmwp/test.jsonl
llm_math/data_loader.py
llm_math/evaluate.py
llm_math/evaluation.py
llm_math/grader.py
llm_math/parser.py
llm_math/prompts/.DS_Store
llm_math/prompts/cot/gsm8k.md
llm_math/prompts/cot/math.md
llm_math/prompts/cot/math_8shot.md
llm_math/prompts/cot/mathqa.md
llm_math/prompts/cot/minerva_math.md
llm_math/prompts/cot/mmlu_stem.md
llm_math/prompts/pal/gsm8k.md
llm_math/prompts/pal/math.md
llm_math/prompts/tora/gsm8k.md
llm_math/prompts/tora/math.md
llm_math/python_executor.py
llm_math/trajectory.py
llm_math/utils.py
llm_math/verify.py
llm_math-0.2.0.dist-info/RECORD
