Metadata-Version: 2.1
Name: llm_math
Version: 0.2.0
Summary: A tool designed to evaluate the performance of large language models on mathematical tasks.
Author-Email: Haoxiang Sun <hxiang.sun@gmail.com>
License: MIT
Requires-Python: >=3.10
Requires-Dist: vllm>=0.6.1
Requires-Dist: word2number
Requires-Dist: antlr4-python3-runtime==4.11.1
Requires-Dist: Pebble
Requires-Dist: timeout-decorator
Requires-Dist: latex2sympy2-llmmath==1.9.1
Requires-Dist: sympy==1.12
